zinmage/__init__.py
zinmage/cli.py
zinmage/converters/__init__.py
zinmage/converters/jpg_to_png.py
zinmage/converters/jpg_to_webp.py
zinmage/converters/png_to_jpg.py
zinmage/utils/__init__.py
zinmage/utils/helpers.py
zinmage-0.1.5.dist-info/licenses/LICENSE
zinmage-0.1.5.dist-info/METADATA
zinmage-0.1.5.dist-info/WHEEL
zinmage-0.1.5.dist-info/entry_points.txt
zinmage-0.1.5.dist-info/top_level.txt
zinmage-0.1.5.dist-info/RECORD
